almvotes/__init__.py
almvotes/admin.py
almvotes/exceptions.py
almvotes/functions.py
almvotes/models.py
almvotes/tests.py
almvotes/views.py
almvotes-1.0.dist-info/DESCRIPTION.rst
almvotes-1.0.dist-info/METADATA
almvotes-1.0.dist-info/RECORD
almvotes-1.0.dist-info/WHEEL
almvotes-1.0.dist-info/metadata.json
almvotes-1.0.dist-info/top_level.txt
almvotos/__init__.py
almvotos/settings.py
almvotos/urls.py
almvotos/wsgi.py
