Metadata-Version: 2.0
Name: almvotes
Version: 1.0
Summary: Libreria para el almacenamiento de los votos en la BD
Home-page: UNKNOWN
Author: Equipo almacenamiento
Author-email: juasanpar@hotmail.com
License: MIT
Download-URL: https://github.com/Proyecto-EGC-G1/Almacenamiento-Votos-EGC-G1/tree/master/project/AlmacenamientoVotos
Platform: UNKNOWN
Requires-Dist: Django (>=1.4)
